nomail/__init__.py
nomail/action.py
nomail/adapter.py
nomail/descriptor.py
nomail/email.py
nomail/email_filter.py
nomail/env.py
nomail/imap.py
nomail/io.py
nomail/output.py
nomail/sanitize.py
nomail/session.py
nomail/util.py
nomail-0.1.1.dist-info/LICENSE.txt
nomail-0.1.1.dist-info/METADATA
nomail-0.1.1.dist-info/WHEEL
nomail-0.1.1.dist-info/RECORD
