Metadata-Version: 2.1
Name: nomail
Version: 0.1.1
Summary: lightweight customizable email filter
Author: Aiden Cullo
Author-email: aidencullo@gmail.com
Requires-Python: >=3.12,<4.0
Classifier: Programming Language :: Python :: 3
Classifier: Programming Language :: Python :: 3.12
